{"cohorts": [{"cohort": "Pre-2022", "initial_count": 67036, "retention": [{"period": "2022-Q1", "count": 67036, "rate": 100.0}, {"period": "2022-Q2", "count": 62497, "rate": 93.2}, {"period": "2022-Q3", "count": 58438, "rate": 87.2}, {"period": "2022-Q4", "count": 55216, "rate": 82.4}, {"period": "2023-Q1", "count": 51479, "rate": 76.8}, {"period": "2023-Q2", "count": 47147, "rate": 70.3}, {"period": "2023-Q3", "count": 42721, "rate": 63.7}, {"period": "2023-Q4", "count": 38217, "rate": 57.0}, {"period": "2024-Q1", "count": 34602, "rate": 51.6}, {"period": "2024-Q2", "count": 29627, "rate": 44.2}, {"period": "2024-Q3", "count": 26892, "rate": 40.1}, {"period": "2024-Q4", "count": 24311, "rate": 36.3}, {"period": "2025-Q1", "count": 21346, "rate": 31.8}, {"period": "2025-Q2", "count": 17934, "rate": 26.8}, {"period": "2025-Q3", "count": 14295, "rate": 21.3}, {"period": "2025-Q4", "count": 10693, "rate": 16.0}, {"period": "2026-Q1", "count": 6527, "rate": 9.7}]}, {"cohort": "2022-Q1", "initial_count": 4065, "retention": [{"period": "2022-Q1", "count": 4065, "rate": 100.0}, {"period": "2022-Q2", "count": 1559, "rate": 38.4}, {"period": "2022-Q3", "count": 1377, "rate": 33.9}, {"period": "2022-Q4", "count": 1227, "rate": 30.2}, {"period": "2023-Q1", "count": 1114, "rate": 27.4}, {"period": "2023-Q2", "count": 946, "rate": 23.3}, {"period": "2023-Q3", "count": 833, "rate": 20.5}, {"period": "2023-Q4", "count": 732, "rate": 18.0}, {"period": "2024-Q1", "count": 638, "rate": 15.7}, {"period": "2024-Q2", "count": 516, "rate": 12.7}, {"period": "2024-Q3", "count": 445, "rate": 10.9}, {"period": "2024-Q4", "count": 391, "rate": 9.6}, {"period": "2025-Q1", "count": 326, "rate": 8.0}, {"period": "2025-Q2", "count": 260, "rate": 6.4}, {"period": "2025-Q3", "count": 190, "rate": 4.7}, {"period": "2025-Q4", "count": 137, "rate": 3.4}, {"period": "2026-Q1", "count": 90, "rate": 2.2}]}, {"cohort": "2022-Q2", "initial_count": 3378, "retention": [{"period": "2022-Q1", "count": 0, "rate": 0.0}, {"period": "2022-Q2", "count": 3378, "rate": 100.0}, {"period": "2022-Q3", "count": 1328, "rate": 39.3}, {"period": "2022-Q4", "count": 1148, "rate": 34.0}, {"period": "2023-Q1", "count": 1067, "rate": 31.6}, {"period": "2023-Q2", "count": 913, "rate": 27.0}, {"period": "2023-Q3", "count": 746, "rate": 22.1}, {"period": "2023-Q4", "count": 609, "rate": 18.0}, {"period": "2024-Q1", "count": 506, "rate": 15.0}, {"period": "2024-Q2", "count": 409, "rate": 12.1}, {"period": "2024-Q3", "count": 357, "rate": 10.6}, {"period": "2024-Q4", "count": 300, "rate": 8.9}, {"period": "2025-Q1", "count": 260, "rate": 7.7}, {"period": "2025-Q2", "count": 212, "rate": 6.3}, {"period": "2025-Q3", "count": 164, "rate": 4.9}, {"period": "2025-Q4", "count": 124, "rate": 3.7}, {"period": "2026-Q1", "count": 64, "rate": 1.9}]}, {"cohort": "2022-Q3", "initial_count": 3087, "retention": [{"period": "2022-Q1", "count": 0, "rate": 0.0}, {"period": "2022-Q2", "count": 0, "rate": 0.0}, {"period": "2022-Q3", "count": 3087, "rate": 100.0}, {"period": "2022-Q4", "count": 1211, "rate": 39.2}, {"period": "2023-Q1", "count": 1094, "rate": 35.4}, {"period": "2023-Q2", "count": 942, "rate": 30.5}, {"period": "2023-Q3", "count": 810, "rate": 26.2}, {"period": "2023-Q4", "count": 674, "rate": 21.8}, {"period": "2024-Q1", "count": 601, "rate": 19.5}, {"period": "2024-Q2", "count": 483, "rate": 15.6}, {"period": "2024-Q3", "count": 421, "rate": 13.6}, {"period": "2024-Q4", "count": 366, "rate": 11.9}, {"period": "2025-Q1", "count": 318, "rate": 10.3}, {"period": "2025-Q2", "count": 261, "rate": 8.5}, {"period": "2025-Q3", "count": 213, "rate": 6.9}, {"period": "2025-Q4", "count": 157, "rate": 5.1}, {"period": "2026-Q1", "count": 97, "rate": 3.1}]}, {"cohort": "2022-Q4", "initial_count": 4671, "retention": [{"period": "2022-Q1", "count": 0, "rate": 0.0}, {"period": "2022-Q2", "count": 0, "rate": 0.0}, {"period": "2022-Q3", "count": 0, "rate": 0.0}, {"period": "2022-Q4", "count": 4671, "rate": 100.0}, {"period": "2023-Q1", "count": 1796, "rate": 38.5}, {"period": "2023-Q2", "count": 1482, "rate": 31.7}, {"period": "2023-Q3", "count": 1241, "rate": 26.6}, {"period": "2023-Q4", "count": 1045, "rate": 22.4}, {"period": "2024-Q1", "count": 895, "rate": 19.2}, {"period": "2024-Q2", "count": 709, "rate": 15.2}, {"period": "2024-Q3", "count": 626, "rate": 13.4}, {"period": "2024-Q4", "count": 541, "rate": 11.6}, {"period": "2025-Q1", "count": 452, "rate": 9.7}, {"period": "2025-Q2", "count": 362, "rate": 7.7}, {"period": "2025-Q3", "count": 271, "rate": 5.8}, {"period": "2025-Q4", "count": 208, "rate": 4.5}, {"period": "2026-Q1", "count": 121, "rate": 2.6}]}, {"cohort": "2023-Q1", "initial_count": 5248, "retention": [{"period": "2022-Q1", "count": 0, "rate": 0.0}, {"period": "2022-Q2", "count": 0, "rate": 0.0}, {"period": "2022-Q3", "count": 0, "rate": 0.0}, {"period": "2022-Q4", "count": 0, "rate": 0.0}, {"period": "2023-Q1", "count": 5248, "rate": 100.0}, {"period": "2023-Q2", "count": 1917, "rate": 36.5}, {"period": "2023-Q3", "count": 1571, "rate": 29.9}, {"period": "2023-Q4", "count": 1263, "rate": 24.1}, {"period": "2024-Q1", "count": 1175, "rate": 22.4}, {"period": "2024-Q2", "count": 907, "rate": 17.3}, {"period": "2024-Q3", "count": 757, "rate": 14.4}, {"period": "2024-Q4", "count": 653, "rate": 12.4}, {"period": "2025-Q1", "count": 562, "rate": 10.7}, {"period": "2025-Q2", "count": 455, "rate": 8.7}, {"period": "2025-Q3", "count": 349, "rate": 6.7}, {"period": "2025-Q4", "count": 237, "rate": 4.5}, {"period": "2026-Q1", "count": 148, "rate": 2.8}]}, {"cohort": "2023-Q2", "initial_count": 3665, "retention": [{"period": "2022-Q1", "count": 0, "rate": 0.0}, {"period": "2022-Q2", "count": 0, "rate": 0.0}, {"period": "2022-Q3", "count": 0, "rate": 0.0}, {"period": "2022-Q4", "count": 0, "rate": 0.0}, {"period": "2023-Q1", "count": 0, "rate": 0.0}, {"period": "2023-Q2", "count": 3665, "rate": 100.0}, {"period": "2023-Q3", "count": 1252, "rate": 34.2}, {"period": "2023-Q4", "count": 989, "rate": 27.0}, {"period": "2024-Q1", "count": 901, "rate": 24.6}, {"period": "2024-Q2", "count": 687, "rate": 18.7}, {"period": "2024-Q3", "count": 567, "rate": 15.5}, {"period": "2024-Q4", "count": 476, "rate": 13.0}, {"period": "2025-Q1", "count": 382, "rate": 10.4}, {"period": "2025-Q2", "count": 315, "rate": 8.6}, {"period": "2025-Q3", "count": 239, "rate": 6.5}, {"period": "2025-Q4", "count": 180, "rate": 4.9}, {"period": "2026-Q1", "count": 113, "rate": 3.1}]}, {"cohort": "2023-Q3", "initial_count": 3052, "retention": [{"period": "2022-Q1", "count": 0, "rate": 0.0}, {"period": "2022-Q2", "count": 0, "rate": 0.0}, {"period": "2022-Q3", "count": 0, "rate": 0.0}, {"period": "2022-Q4", "count": 0, "rate": 0.0}, {"period": "2023-Q1", "count": 0, "rate": 0.0}, {"period": "2023-Q2", "count": 0, "rate": 0.0}, {"period": "2023-Q3", "count": 3052, "rate": 100.0}, {"period": "2023-Q4", "count": 872, "rate": 28.6}, {"period": "2024-Q1", "count": 768, "rate": 25.2}, {"period": "2024-Q2", "count": 547, "rate": 17.9}, {"period": "2024-Q3", "count": 447, "rate": 14.6}, {"period": "2024-Q4", "count": 379, "rate": 12.4}, {"period": "2025-Q1", "count": 304, "rate": 10.0}, {"period": "2025-Q2", "count": 251, "rate": 8.2}, {"period": "2025-Q3", "count": 193, "rate": 6.3}, {"period": "2025-Q4", "count": 148, "rate": 4.8}, {"period": "2026-Q1", "count": 95, "rate": 3.1}]}, {"cohort": "2023-Q4", "initial_count": 2002, "retention": [{"period": "2022-Q1", "count": 0, "rate": 0.0}, {"period": "2022-Q2", "count": 0, "rate": 0.0}, {"period": "2022-Q3", "count": 0, "rate": 0.0}, {"period": "2022-Q4", "count": 0, "rate": 0.0}, {"period": "2023-Q1", "count": 0, "rate": 0.0}, {"period": "2023-Q2", "count": 0, "rate": 0.0}, {"period": "2023-Q3", "count": 0, "rate": 0.0}, {"period": "2023-Q4", "count": 2002, "rate": 100.0}, {"period": "2024-Q1", "count": 593, "rate": 29.6}, {"period": "2024-Q2", "count": 430, "rate": 21.5}, {"period": "2024-Q3", "count": 346, "rate": 17.3}, {"period": "2024-Q4", "count": 293, "rate": 14.6}, {"period": "2025-Q1", "count": 245, "rate": 12.2}, {"period": "2025-Q2", "count": 203, "rate": 10.1}, {"period": "2025-Q3", "count": 156, "rate": 7.8}, {"period": "2025-Q4", "count": 116, "rate": 5.8}, {"period": "2026-Q1", "count": 78, "rate": 3.9}]}, {"cohort": "2024-Q1", "initial_count": 2559, "retention": [{"period": "2022-Q1", "count": 0, "rate": 0.0}, {"period": "2022-Q2", "count": 0, "rate": 0.0}, {"period": "2022-Q3", "count": 0, "rate": 0.0}, {"period": "2022-Q4", "count": 0, "rate": 0.0}, {"period": "2023-Q1", "count": 0, "rate": 0.0}, {"period": "2023-Q2", "count": 0, "rate": 0.0}, {"period": "2023-Q3", "count": 0, "rate": 0.0}, {"period": "2023-Q4", "count": 0, "rate": 0.0}, {"period": "2024-Q1", "count": 2559, "rate": 100.0}, {"period": "2024-Q2", "count": 654, "rate": 25.6}, {"period": "2024-Q3", "count": 537, "rate": 21.0}, {"period": "2024-Q4", "count": 441, "rate": 17.2}, {"period": "2025-Q1", "count": 372, "rate": 14.5}, {"period": "2025-Q2", "count": 301, "rate": 11.8}, {"period": "2025-Q3", "count": 234, "rate": 9.1}, {"period": "2025-Q4", "count": 167, "rate": 6.5}, {"period": "2026-Q1", "count": 99, "rate": 3.9}]}, {"cohort": "2024-Q2", "initial_count": 1063, "retention": [{"period": "2022-Q1", "count": 0, "rate": 0.0}, {"period": "2022-Q2", "count": 0, "rate": 0.0}, {"period": "2022-Q3", "count": 0, "rate": 0.0}, {"period": "2022-Q4", "count": 0, "rate": 0.0}, {"period": "2023-Q1", "count": 0, "rate": 0.0}, {"period": "2023-Q2", "count": 0, "rate": 0.0}, {"period": "2023-Q3", "count": 0, "rate": 0.0}, {"period": "2023-Q4", "count": 0, "rate": 0.0}, {"period": "2024-Q1", "count": 0, "rate": 0.0}, {"period": "2024-Q2", "count": 1063, "rate": 100.0}, {"period": "2024-Q3", "count": 242, "rate": 22.8}, {"period": "2024-Q4", "count": 198, "rate": 18.6}, {"period": "2025-Q1", "count": 172, "rate": 16.2}, {"period": "2025-Q2", "count": 129, "rate": 12.1}, {"period": "2025-Q3", "count": 111, "rate": 10.4}, {"period": "2025-Q4", "count": 86, "rate": 8.1}, {"period": "2026-Q1", "count": 44, "rate": 4.1}]}, {"cohort": "2024-Q3", "initial_count": 1112, "retention": [{"period": "2022-Q1", "count": 0, "rate": 0.0}, {"period": "2022-Q2", "count": 0, "rate": 0.0}, {"period": "2022-Q3", "count": 0, "rate": 0.0}, {"period": "2022-Q4", "count": 0, "rate": 0.0}, {"period": "2023-Q1", "count": 0, "rate": 0.0}, {"period": "2023-Q2", "count": 0, "rate": 0.0}, {"period": "2023-Q3", "count": 0, "rate": 0.0}, {"period": "2023-Q4", "count": 0, "rate": 0.0}, {"period": "2024-Q1", "count": 0, "rate": 0.0}, {"period": "2024-Q2", "count": 0, "rate": 0.0}, {"period": "2024-Q3", "count": 1112, "rate": 100.0}, {"period": "2024-Q4", "count": 252, "rate": 22.7}, {"period": "2025-Q1", "count": 219, "rate": 19.7}, {"period": "2025-Q2", "count": 153, "rate": 13.8}, {"period": "2025-Q3", "count": 120, "rate": 10.8}, {"period": "2025-Q4", "count": 80, "rate": 7.2}, {"period": "2026-Q1", "count": 37, "rate": 3.3}]}, {"cohort": "2024-Q4", "initial_count": 1150, "retention": [{"period": "2022-Q1", "count": 0, "rate": 0.0}, {"period": "2022-Q2", "count": 0, "rate": 0.0}, {"period": "2022-Q3", "count": 0, "rate": 0.0}, {"period": "2022-Q4", "count": 0, "rate": 0.0}, {"period": "2023-Q1", "count": 0, "rate": 0.0}, {"period": "2023-Q2", "count": 0, "rate": 0.0}, {"period": "2023-Q3", "count": 0, "rate": 0.0}, {"period": "2023-Q4", "count": 0, "rate": 0.0}, {"period": "2024-Q1", "count": 0, "rate": 0.0}, {"period": "2024-Q2", "count": 0, "rate": 0.0}, {"period": "2024-Q3", "count": 0, "rate": 0.0}, {"period": "2024-Q4", "count": 1150, "rate": 100.0}, {"period": "2025-Q1", "count": 250, "rate": 21.7}, {"period": "2025-Q2", "count": 178, "rate": 15.5}, {"period": "2025-Q3", "count": 135, "rate": 11.7}, {"period": "2025-Q4", "count": 99, "rate": 8.6}, {"period": "2026-Q1", "count": 49, "rate": 4.3}]}, {"cohort": "2025-Q1", "initial_count": 885, "retention": [{"period": "2022-Q1", "count": 0, "rate": 0.0}, {"period": "2022-Q2", "count": 0, "rate": 0.0}, {"period": "2022-Q3", "count": 0, "rate": 0.0}, {"period": "2022-Q4", "count": 0, "rate": 0.0}, {"period": "2023-Q1", "count": 0, "rate": 0.0}, {"period": "2023-Q2", "count": 0, "rate": 0.0}, {"period": "2023-Q3", "count": 0, "rate": 0.0}, {"period": "2023-Q4", "count": 0, "rate": 0.0}, {"period": "2024-Q1", "count": 0, "rate": 0.0}, {"period": "2024-Q2", "count": 0, "rate": 0.0}, {"period": "2024-Q3", "count": 0, "rate": 0.0}, {"period": "2024-Q4", "count": 0, "rate": 0.0}, {"period": "2025-Q1", "count": 885, "rate": 100.0}, {"period": "2025-Q2", "count": 232, "rate": 26.2}, {"period": "2025-Q3", "count": 163, "rate": 18.4}, {"period": "2025-Q4", "count": 106, "rate": 12.0}, {"period": "2026-Q1", "count": 76, "rate": 8.6}]}, {"cohort": "2025-Q2", "initial_count": 995, "retention": [{"period": "2022-Q1", "count": 0, "rate": 0.0}, {"period": "2022-Q2", "count": 0, "rate": 0.0}, {"period": "2022-Q3", "count": 0, "rate": 0.0}, {"period": "2022-Q4", "count": 0, "rate": 0.0}, {"period": "2023-Q1", "count": 0, "rate": 0.0}, {"period": "2023-Q2", "count": 0, "rate": 0.0}, {"period": "2023-Q3", "count": 0, "rate": 0.0}, {"period": "2023-Q4", "count": 0, "rate": 0.0}, {"period": "2024-Q1", "count": 0, "rate": 0.0}, {"period": "2024-Q2", "count": 0, "rate": 0.0}, {"period": "2024-Q3", "count": 0, "rate": 0.0}, {"period": "2024-Q4", "count": 0, "rate": 0.0}, {"period": "2025-Q1", "count": 0, "rate": 0.0}, {"period": "2025-Q2", "count": 995, "rate": 100.0}, {"period": "2025-Q3", "count": 194, "rate": 19.5}, {"period": "2025-Q4", "count": 121, "rate": 12.2}, {"period": "2026-Q1", "count": 70, "rate": 7.0}]}, {"cohort": "2025-Q3", "initial_count": 853, "retention": [{"period": "2022-Q1", "count": 0, "rate": 0.0}, {"period": "2022-Q2", "count": 0, "rate": 0.0}, {"period": "2022-Q3", "count": 0, "rate": 0.0}, {"period": "2022-Q4", "count": 0, "rate": 0.0}, {"period": "2023-Q1", "count": 0, "rate": 0.0}, {"period": "2023-Q2", "count": 0, "rate": 0.0}, {"period": "2023-Q3", "count": 0, "rate": 0.0}, {"period": "2023-Q4", "count": 0, "rate": 0.0}, {"period": "2024-Q1", "count": 0, "rate": 0.0}, {"period": "2024-Q2", "count": 0, "rate": 0.0}, {"period": "2024-Q3", "count": 0, "rate": 0.0}, {"period": "2024-Q4", "count": 0, "rate": 0.0}, {"period": "2025-Q1", "count": 0, "rate": 0.0}, {"period": "2025-Q2", "count": 0, "rate": 0.0}, {"period": "2025-Q3", "count": 853, "rate": 100.0}, {"period": "2025-Q4", "count": 123, "rate": 14.4}, {"period": "2026-Q1", "count": 78, "rate": 9.1}]}, {"cohort": "2025-Q4", "initial_count": 602, "retention": [{"period": "2022-Q1", "count": 0, "rate": 0.0}, {"period": "2022-Q2", "count": 0, "rate": 0.0}, {"period": "2022-Q3", "count": 0, "rate": 0.0}, {"period": "2022-Q4", "count": 0, "rate": 0.0}, {"period": "2023-Q1", "count": 0, "rate": 0.0}, {"period": "2023-Q2", "count": 0, "rate": 0.0}, {"period": "2023-Q3", "count": 0, "rate": 0.0}, {"period": "2023-Q4", "count": 0, "rate": 0.0}, {"period": "2024-Q1", "count": 0, "rate": 0.0}, {"period": "2024-Q2", "count": 0, "rate": 0.0}, {"period": "2024-Q3", "count": 0, "rate": 0.0}, {"period": "2024-Q4", "count": 0, "rate": 0.0}, {"period": "2025-Q1", "count": 0, "rate": 0.0}, {"period": "2025-Q2", "count": 0, "rate": 0.0}, {"period": "2025-Q3", "count": 0, "rate": 0.0}, {"period": "2025-Q4", "count": 602, "rate": 100.0}, {"period": "2026-Q1", "count": 69, "rate": 11.5}]}, {"cohort": "2026-Q1", "initial_count": 684, "retention": [{"period": "2022-Q1", "count": 0, "rate": 0.0}, {"period": "2022-Q2", "count": 0, "rate": 0.0}, {"period": "2022-Q3", "count": 0, "rate": 0.0}, {"period": "2022-Q4", "count": 0, "rate": 0.0}, {"period": "2023-Q1", "count": 0, "rate": 0.0}, {"period": "2023-Q2", "count": 0, "rate": 0.0}, {"period": "2023-Q3", "count": 0, "rate": 0.0}, {"period": "2023-Q4", "count": 0, "rate": 0.0}, {"period": "2024-Q1", "count": 0, "rate": 0.0}, {"period": "2024-Q2", "count": 0, "rate": 0.0}, {"period": "2024-Q3", "count": 0, "rate": 0.0}, {"period": "2024-Q4", "count": 0, "rate": 0.0}, {"period": "2025-Q1", "count": 0, "rate": 0.0}, {"period": "2025-Q2", "count": 0, "rate": 0.0}, {"period": "2025-Q3", "count": 0, "rate": 0.0}, {"period": "2025-Q4", "count": 0, "rate": 0.0}, {"period": "2026-Q1", "count": 684, "rate": 100.0}]}], "periods": ["2022-Q1", "2022-Q2", "2022-Q3", "2022-Q4", "2023-Q1", "2023-Q2", "2023-Q3", "2023-Q4", "2024-Q1", "2024-Q2", "2024-Q3", "2024-Q4", "2025-Q1", "2025-Q2", "2025-Q3", "2025-Q4", "2026-Q1"]}